
<!-- 
    Nuevo XML con el elemento padre catalogo:
        El catalogo contendrá productos (al menos 5) con la siguiente información:
            - nombre
            - precio
            - descripcion
            - categoria (como atributo)
            - disponible (como atributo)
        *Incluye comentarios para cada sección
        **Podeis utilizar <!CDATA[]> dentro de las etiquetas por si quereis escapar algún dato en concreto
 -->


<catalogo     
    xmlns:xsi="https://w3.org/2001/XMLSchema-instance"
    xsi:noNamespaceSchemaLocation="./catalogoSchema.xsd"
>    
    <producto categoria="" disponible="">
        <nombre></nombre>
        <precio></precio>
        <descripcion></descripcion>
    </producto>

    <producto categoria="" disponible="">
        <nombre></nombre>
        <precio></precio>
        <descripcion></descripcion>
    </producto>

    <producto categoria="" disponible="">
        <nombre></nombre>
        <precio></precio>
        <descripcion></descripcion>
    </producto>  

    <producto categoria="" disponible="">
        <nombre></nombre>
        <precio></precio>
        <descripcion></descripcion>
    </producto>   

    <producto categoria="" disponible="">
        <nombre></nombre>
        <precio></precio>
        <descripcion></descripcion>
    </producto>                 
</catalogo>